Metadata-Version: 2.1
Name: mathy
Version: 0.9.6
Summary: Mathy - RL environments for solving math problems step-by-step
Home-page: https://mathy.ai
Author: Justin DuJardin
Author-email: justin@dujardinconsulting.com
License: All rights reserved
Keywords: math
Classifier: Programming Language :: Python :: 3
Classifier: License :: OSI Approved :: MIT License
Classifier: Operating System :: OS Independent
Classifier: Development Status :: 2 - Pre-Alpha
Requires-Python: >=3.6
Requires-Dist: numpy
Requires-Dist: colr
Requires-Dist: srsly
Requires-Dist: typer <0.7.0,>=0.6.1
Requires-Dist: wasabi
Requires-Dist: mathy-core <0.10.0,>=0.9.1
Requires-Dist: mathy-envs[gym] <0.13.0,>=0.12.0
Requires-Dist: gymnasium
Requires-Dist: tqdm >=4.43.0
Requires-Dist: xxhash
Requires-Dist: numba
Requires-Dist: dataclasses <1.0,>=0.6 ; python_version < "3.7"
Requires-Dist: typing-extensions <4.0.0.0,>=3.7.4.1 ; python_version < "3.7"
Provides-Extra: all
Requires-Dist: mypy ; extra == 'all'
Requires-Dist: pytest ; extra == 'all'
Requires-Dist: pytest-cov ; extra == 'all'
Requires-Dist: black <22.2.0 ; extra == 'all'
Requires-Dist: isort ; extra == 'all'
Requires-Dist: autoflake ; extra == 'all'
Requires-Dist: flake8 ; extra == 'all'
Requires-Dist: snakeviz ; extra == 'all'
Provides-Extra: dev
Requires-Dist: mypy ; extra == 'dev'
Requires-Dist: pytest ; extra == 'dev'
Requires-Dist: pytest-cov ; extra == 'dev'
Requires-Dist: black <22.2.0 ; extra == 'dev'
Requires-Dist: isort ; extra == 'dev'
Requires-Dist: autoflake ; extra == 'dev'
Requires-Dist: flake8 ; extra == 'dev'
Requires-Dist: snakeviz ; extra == 'dev'
